arc_reactor/__init__.py
arc_reactor/__main__.py
arc_reactor/cli/__init__.py
arc_reactor/cli/clean/__init__.py
arc_reactor/cli/clean/__main__.py
arc_reactor/cli/clean/help/__init__.py
arc_reactor/cli/clean/help/__main__.py
arc_reactor/cli/help/__init__.py
arc_reactor/cli/help/__main__.py
arc_reactor/cli/help/argumentNotMatched.py
arc_reactor/cli/init/__init__.py
arc_reactor/cli/init/__main__.py
arc_reactor/cli/init/downloader.py
arc_reactor/cli/init/frameworkZip.py
arc_reactor/cli/init/help/__init__.py
arc_reactor/cli/init/help/__main__.py
arc_reactor/cli/start/__init__.py
arc_reactor/cli/start/__main__.py
arc_reactor/cli/start/help/__init__.py
arc_reactor/cli/start/help/__main__.py
arc_reactor/cli/test/__init__.py
arc_reactor/cli/test/__main__.py
arc_reactor/cli/test/help/__init__.py
arc_reactor/cli/test/help/__main__.py
arc_reactor/cli/update/__init__.py
arc_reactor/cli/update/__main__.py
arc_reactor/cli/update/help/__init__.py
arc_reactor/cli/update/help/__main__.py
arc_reactor/decorator/__init__.py
arc_reactor/decorator/component.py
arc_reactor/decorator/disablePrint.py
arc_reactor/decorator/ensure_annotation.py
arc_reactor/decorator/entryExitMethodLoadd.py
arc_reactor/decorator/exceptionHandler.py
arc_reactor/decorator/hystrixHandler.py
arc_reactor/decorator/restrict.py
arc_reactor/decorator/startArcReactorApplication.py
arc_reactor/service/__init__.py
arc_reactor/service/sysService.py
arc_reactor/system_config/__init__.py
arc_reactor/system_config/proprtties.py
arc_reactor/utility/__init__.py
arc_reactor/utility/commonUtils.py
arc_reactor/utility/configReader.py
arc_reactor/utility/stringUtils.py
arc_reactor-1.0.10.dist-info/LICENSE
arc_reactor-1.0.10.dist-info/METADATA
arc_reactor-1.0.10.dist-info/WHEEL
arc_reactor-1.0.10.dist-info/entry_points.txt
arc_reactor-1.0.10.dist-info/top_level.txt
arc_reactor-1.0.10.dist-info/RECORD
